voit/__init__.py
voit/_analytical_light_estimation.py
voit/_depth_data.py
voit/_envmap_internal.py
voit/_errors.py
voit/_fmt_checks_internal.py
voit/_insertion_main.py
voit/_light_conf_internal.py
voit/_logging_internal.py
voit/_math_internal.py
voit/_normal_estimation.py
voit/_panda3d_util_internal.py
voit/_render_pipeline_internal.py
voit/_vectors.py
voit/_complexerpbr_internal/__init__.py
voit/_complexerpbr_internal/_ibl_funcs_cpu.py
voit/_complexerpbr_internal/_pipeline_utils.py
voit/_complexerpbr_internal/_shaderutils.py
voit/_complexerpbr_internal/envmap.py
voit/_complexerpbr_internal/envpool.py
voit/_complexerpbr_internal/logging.py
voit/_complexerpbr_internal/py.typed
voit/_complexerpbr_internal/utils.py
voit/_complexerpbr_internal/version.py
voit/_complexerpbr_internal/shaders/post.vert
voit/_complexerpbr_internal/shaders/shadow.frag
voit/_complexerpbr_internal/shaders/shadow.vert
voit/_complexerpbr_internal/shaders/simplepbr.frag
voit/_complexerpbr_internal/shaders/simplepbr.vert
voit/_complexerpbr_internal/shaders/tonemap.frag
voit/_complexerpbr_internal/textures/brdf_lut.txo
voit/_ctx_estimation_internal/BilateralGrid.py
voit/_ctx_estimation_internal/BilateralLayer.py
voit/_ctx_estimation_internal/__init__.py
voit/_ctx_estimation_internal/_predict.py
voit/_ctx_estimation_internal/models.py
voit/resources/sphere_surface_lut.npy
voit/serialized/__init__.py
voit/serialized/_serialized.py
voit_inserter-0.1.1.dist-info/LICENSE.txt
voit_inserter-0.1.1.dist-info/METADATA
voit_inserter-0.1.1.dist-info/WHEEL
voit_inserter-0.1.1.dist-info/top_level.txt
voit_inserter-0.1.1.dist-info/RECORD
