Metadata-Version: 2.2
Name: voit-inserter
Version: 0.1.1
Summary: VOIT = Virtual Object Insertion Tooolkit.
License: MIT License
Project-URL: Homepage, https://github.com/mntusr/voit
Keywords: object insertion
Classifier: License :: OSI Approved :: MIT License
Classifier: Development Status :: 3 - Alpha
Requires-Python: >=3.10
License-File: LICENSE.txt
Requires-Dist: panda3d>=1.10.14
Requires-Dist: numpy>=1.22.4
Requires-Dist: opencv-python>=4.6.0
Requires-Dist: safetensors>=0.4.0
Requires-Dist: scipy>=1.12.0
Requires-Dist: plotly>=5.22.0
Requires-Dist: panda3d-gltf>=1.1.0
